queue_bot/__init__.py
queue_bot/bot.py
queue_bot/admin/__init__.py
queue_bot/admin/admin.py
queue_bot/admin/states.py
queue_bot/base/__init__.py
queue_bot/base/account.py
queue_bot/base/klient.py
queue_bot/base/monitoring.py
queue_bot/base/parser.py
queue_bot/base/scheduler.py
queue_bot/base/template.py
queue_bot/db/__init__.py
queue_bot/db/db_init_car.py
queue_bot/db/models.py
queue_bot/handlers/__init__.py
queue_bot/handlers/account/__init__.py
queue_bot/handlers/account/account.py
queue_bot/handlers/base/__init__.py
queue_bot/handlers/base/base.py
queue_bot/handlers/beniakoni/__init__.py
queue_bot/handlers/beniakoni/beniakoni.py
queue_bot/handlers/berestovitsa/__init__.py
queue_bot/handlers/berestovitsa/berestovitsa.py
queue_bot/handlers/brest/__init__.py
queue_bot/handlers/brest/brest.py
queue_bot/handlers/checkpoint_info/__init__.py
queue_bot/handlers/checkpoint_info/checkpoint_info.py
queue_bot/handlers/grigorovshcina/__init__.py
queue_bot/handlers/grigorovshcina/grigorovshcina.py
queue_bot/handlers/kamenny_log/__init__.py
queue_bot/handlers/kamenny_log/kamenny_log.py
queue_bot/handlers/kotlovka/__init__.py
queue_bot/handlers/kotlovka/kotlovka.py
queue_bot/handlers/monitoring/__init__.py
queue_bot/handlers/monitoring/monitiring.py
queue_bot/handlers/urbany/__init__.py
queue_bot/handlers/urbany/urbany.py
queue_bot/keyboard/__init__.py
queue_bot/keyboard/base_keyboard/__init__.py
queue_bot/keyboard/base_keyboard/base.py
queue_bot/keyboard/beniakoni_keyboard/__init__.py
queue_bot/keyboard/beniakoni_keyboard/beniakoni.py
queue_bot/keyboard/berestovitsa_keyboard/__init__.py
queue_bot/keyboard/berestovitsa_keyboard/berestovitsa.py
queue_bot/keyboard/brest_keyboard/__init__.py
queue_bot/keyboard/brest_keyboard/brest.py
queue_bot/keyboard/grigorovshcina_keyboard/__init__.py
queue_bot/keyboard/grigorovshcina_keyboard/grigorovshcina.py
queue_bot/keyboard/kamenny_log_keyboard/__init__.py
queue_bot/keyboard/kamenny_log_keyboard/kamenny_log.py
noumak_border_bot-0.0.38.dist-info/LICENSE
noumak_border_bot-0.0.38.dist-info/METADATA
noumak_border_bot-0.0.38.dist-info/WHEEL
noumak_border_bot-0.0.38.dist-info/entry_points.txt
noumak_border_bot-0.0.38.dist-info/top_level.txt
noumak_border_bot-0.0.38.dist-info/RECORD
