Metadata-Version: 2.1
Name: noumak-border-bot
Version: 0.0.38
Summary: A bot tracking queues at the botder
Home-page: https://telegra.ph/FAQ-03-10-12
Author: Naumowich Daniel
Author-email: naumovichdaniel@yandex.ru
License: Телеграм бот @RBqueue_bot не является официальным, а лишь любительским, ответственность за подленность информации не несет.
Platform: UNKNOWN
Classifier: Development Status :: 5 - Production/Stable
Requires-Python: >=3.9
License-File: LICENSE
Requires-Dist: APScheduler (==3.10.0)
Requires-Dist: aiofiles (==22.1.0)
Requires-Dist: aiogram (==2.25.1)
Requires-Dist: asyncpg (==0.27.0)
Requires-Dist: python-crontab (==2.7.1)
Requires-Dist: python-dotenv (==0.21.1)
Requires-Dist: redis (==4.5.1)
Requires-Dist: tortoise-orm (==0.19.3)
